flexpolyline_pbapi/__init__.py
flexpolyline_pbapi/decoding.py
flexpolyline_pbapi/encoding.py
python_flexpolyline_pbapi-0.2.1.dist-info/LICENSE
python_flexpolyline_pbapi-0.2.1.dist-info/METADATA
python_flexpolyline_pbapi-0.2.1.dist-info/WHEEL
python_flexpolyline_pbapi-0.2.1.dist-info/top_level.txt
python_flexpolyline_pbapi-0.2.1.dist-info/RECORD
