Metadata-Version: 2.1
Name: python-flexpolyline-pbapi
Version: 0.2.1
Summary: Flexible Polyline encoding (PBAPI extension)
Author: decitre
License: MIT
Project-URL: Source, https://github.com/decitre/python-flexpolyline-pbapi.git
Classifier: Intended Audience :: Developers
Classifier: Programming Language :: Python :: 3 :: Only
Classifier: Programming Language :: Python :: 3.6
Classifier: Programming Language :: Python :: 3.7
Classifier: Programming Language :: Python :: 3.8
Classifier: Programming Language :: Python :: 3.9
Classifier: Programming Language :: Python :: 3.10
Classifier: License :: OSI Approved :: MIT License
Classifier: Operating System :: OS Independent
License-File: LICENSE
